hornet/__init__.py
hornet/digraph.py
hornet/node.py
hornet/protocol.py
hornet/state.py
graphviz_hornet-0.0.6.dist-info/LICENSE
graphviz_hornet-0.0.6.dist-info/METADATA
graphviz_hornet-0.0.6.dist-info/WHEEL
graphviz_hornet-0.0.6.dist-info/top_level.txt
graphviz_hornet-0.0.6.dist-info/RECORD
