Metadata-Version: 2.1
Name: graphviz-hornet
Version: 0.0.6
License: MIT License        
License-File: LICENSE
Requires-Dist: graphviz
Provides-Extra: dev
Requires-Dist: build ; extra == 'dev'
Requires-Dist: twine ; extra == 'dev'
